snowflakemagic/__init__.py
snowflakemagic/snowflakemagic.py
snowflakemagic-1.0.1.dist-info/METADATA
snowflakemagic-1.0.1.dist-info/WHEEL
snowflakemagic-1.0.1.dist-info/top_level.txt
snowflakemagic-1.0.1.dist-info/zip-safe
snowflakemagic-1.0.1.dist-info/RECORD
