Metadata-Version: 2.1
Name: snowflakemagic
Version: 1.0.1
Summary: IPython magic function for Snowflake Query Language (SQL)
Home-page: https://github.com/dtPaTh/snowflakemagic
Author: Patrick Thurner
Author-email: patrick.thurner@gmail.com
License: MIT
Keywords: Notebook,Jupyter,Snowflake
Classifier: License :: OSI Approved :: MIT License
Classifier: Programming Language :: Python :: 3
Requires-Dist: ipython
Requires-Dist: jupyter
Requires-Dist: python-dotenv
Requires-Dist: snowflake-connector-python
